{
    "name": "Global Information",
    "numberOfRequests": {
        "total": 1196,
        "ok": 1196,
        "ko": 0
    },
    "minResponseTime": {
        "total": 102,
        "ok": 102,
        "ko": 0
    },
    "maxResponseTime": {
        "total": 1892,
        "ok": 1892,
        "ko": 0
    },
    "meanResponseTime": {
        "total": 238,
        "ok": 238,
        "ko": 0
    },
    "standardDeviation": {
        "total": 185,
        "ok": 185,
        "ko": 0
    },
    "percentiles1": {
        "total": 155,
        "ok": 155,
        "ko": 0
    },
    "percentiles2": {
        "total": 258,
        "ok": 258,
        "ko": 0
    },
    "percentiles3": {
        "total": 596,
        "ok": 596,
        "ko": 0
    },
    "percentiles4": {
        "total": 1005,
        "ok": 1005,
        "ko": 0
    },
    "group1": {
    "name": "t < 800 ms",
    "count": 1166,
    "percentage": 97
},
    "group2": {
    "name": "800 ms < t < 1200 ms",
    "count": 26,
    "percentage": 2
},
    "group3": {
    "name": "t > 1200 ms",
    "count": 4,
    "percentage": 0
},
    "group4": {
    "name": "failed",
    "count": 0,
    "percentage": 0
},
    "meanNumberOfRequestsPerSecond": {
        "total": 3.986666666666667,
        "ok": 3.986666666666667,
        "ko": 0
    }
}